wzdx/__init__.py
wzdx/combination/__init__.py
wzdx/combination/attenuator.py
wzdx/combination/combine_wzdx.py
wzdx/raw_to_standard/__init__.py
wzdx/raw_to_standard/geotab_avl.py
wzdx/raw_to_standard/icone.py
wzdx/raw_to_standard/navjoy_568.py
wzdx/raw_to_standard/planned_events.py
wzdx/sample_files/__init__.py
wzdx/sample_files/validation_schema/__init__.py
wzdx/sample_files/validation_schema/road_restriction_v40_feed.py
wzdx/sample_files/validation_schema/wzdx_v31_feed.py
wzdx/sample_files/validation_schema/wzdx_v40_feed.py
wzdx/standard_to_enhanced/__init__.py
wzdx/standard_to_enhanced/cotrip_translator.py
wzdx/standard_to_enhanced/geotab_avl_translator.py
wzdx/standard_to_enhanced/icone_translator.py
wzdx/standard_to_enhanced/navjoy_translator.py
wzdx/standard_to_enhanced/planned_events_translator.py
wzdx/tools/__init__.py
wzdx/tools/array_tools.py
wzdx/tools/cdot_geospatial_api.py
wzdx/tools/count_datastore.py
wzdx/tools/date_tools.py
wzdx/tools/path_history_compression.py
wzdx/tools/polygon_tools.py
wzdx/tools/test_cdot_geospatial_api.py
wzdx/tools/wzdx_translator.py
wzdx/util/__init__.py
wzdx/util/collections.py
cdot_wzdx_translator-1.1.4.dist-info/LICENSE.md
cdot_wzdx_translator-1.1.4.dist-info/METADATA
cdot_wzdx_translator-1.1.4.dist-info/WHEEL
cdot_wzdx_translator-1.1.4.dist-info/top_level.txt
cdot_wzdx_translator-1.1.4.dist-info/RECORD
