Metadata-Version: 2.1
Name: cdot-wzdx-translator
Version: 1.1.4
Summary: CDOT Work Zone WZDx Translators
Author: CDOT
Author-email: CDOT_rtdh_prod@state.co.us
Keywords: python,wzdx
Classifier: Development Status :: 4 - Beta
Classifier: Programming Language :: Python :: 3
Classifier: Operating System :: Microsoft :: Windows
License-File: LICENSE.md
Requires-Dist: xmltodict
Requires-Dist: jsonschema
Requires-Dist: python-dateutil
Requires-Dist: shapely
Requires-Dist: geopy
Requires-Dist: pyproj
Requires-Dist: numpy
Requires-Dist: requests
Requires-Dist: pytz
